Disc_Hub_DIA_FDR/LDA.py
Disc_Hub_DIA_FDR/XGBoost.py
Disc_Hub_DIA_FDR/__init__.py
Disc_Hub_DIA_FDR/dynamic_weighting.py
Disc_Hub_DIA_FDR/evaluate.py
Disc_Hub_DIA_FDR/main.py
Disc_Hub_DIA_FDR/mlp_dia_nn.py
Disc_Hub_DIA_FDR/models.py
Disc_Hub_DIA_FDR/svm.py
Disc_Hub_DIA_FDR/train.py
disc_hub_dia_fdr-0.3.4.dist-info/licenses/LICENSE
disc_hub_dia_fdr-0.3.4.dist-info/METADATA
disc_hub_dia_fdr-0.3.4.dist-info/WHEEL
disc_hub_dia_fdr-0.3.4.dist-info/top_level.txt
disc_hub_dia_fdr-0.3.4.dist-info/RECORD
