Metadata-Version: 2.4
Name: Disc_Hub_DIA_FDR
Version: 0.3.4
Summary: A package for Disc Hub Data Integration Analysis
Author: Yiwen Yu
License-File: LICENSE
Requires-Dist: numpy
Requires-Dist: matplotlib
Requires-Dist: pandas
Requires-Dist: pyarrow==19.0.0
Requires-Dist: torch>=2.6.0
Requires-Dist: xgboost
Requires-Dist: scikit-learn
Dynamic: author
Dynamic: license-file
Dynamic: requires-dist
Dynamic: summary
